<annotation>
	<folder>Images</folder>
	<filename>bag53.jpg</filename>
	<path>/home/mattrix/Monk_Object_Detection/example_notebooks/sample_dataset/oyster_bag/Images/bag53.jpg</path>
	<source>
		<database>Unknown</database>
	</source>
	<size>
		<width>187</width>
		<height>127</height>
		<depth>3</depth>
	</size>
	<segmented>0</segmented>
	<object>
		<name>bag</name>
		<pose>Unspecified</pose>
		<truncated>1</truncated>
		<difficult>0</difficult>
		<bndbox>
			<xmin>1</xmin>
			<ymin>9</ymin>
			<xmax>184</xmax>
			<ymax>122</ymax>
		</bndbox>
	</object>
</annotation>
